<?xml version="1.0" encoding="UTF-8"?>
<graph xmlns="http://www.xces.org/ns/GrAF/1.0/">
    <header>
        <tagsDecl>
            <tagUsage gi="objective-speech-event" occurs="13"/>
            <tagUsage gi="attitude" occurs="14"/>
            <tagUsage gi="inside" occurs="20"/>
            <tagUsage gi="target" occurs="14"/>
            <tagUsage gi="split" occurs="23"/>
            <tagUsage gi="expressive-subjectivity" occurs="12"/>
            <tagUsage gi="direct-subjective" occurs="11"/>
            <tagUsage gi="agent" occurs="5"/>
        </tagsDecl>
        <annotationSets>
            <annotationSet name="mpqa" type="http://www.cs.pitt.edu/mpqa/"/>
        </annotationSets>
    </header>
    <region xml:id="r10" anchors="18 31"/>
    <region xml:id="r12" anchors="18 18"/>
    <region xml:id="r8" anchors="18 18"/>
    <region xml:id="r6" anchors="18 18"/>
    <region xml:id="r1" anchors="18 18"/>
    <region xml:id="r16" anchors="38 48"/>
    <region xml:id="r18" anchors="38 42"/>
    <region xml:id="r21" anchors="38 38"/>
    <region xml:id="r14" anchors="38 38"/>
    <region xml:id="r23" anchors="43 47"/>
    <region xml:id="r27" anchors="55 134"/>
    <region xml:id="r25" anchors="55 55"/>
    <region xml:id="r29" anchors="133 134"/>
    <region xml:id="r31" anchors="141 186"/>
    <region xml:id="r33" anchors="141 141"/>
    <region xml:id="r35" anchors="185 186"/>
    <region xml:id="r37" anchors="193 389"/>
    <region xml:id="r39" anchors="193 222"/>
    <region xml:id="r41" anchors="193 197"/>
    <region xml:id="r43" anchors="193 193"/>
    <region xml:id="r45" anchors="198 389"/>
    <region xml:id="r47" anchors="236 275"/>
    <region xml:id="r49" anchors="388 389"/>
    <region xml:id="r51" anchors="390 456"/>
    <region xml:id="r54" anchors="390 390"/>
    <region xml:id="r56" anchors="394 413"/>
    <region xml:id="r58" anchors="433 455"/>
    <region xml:id="r60" anchors="455 456"/>
    <region xml:id="r62" anchors="457 1017"/>
    <region xml:id="r64" anchors="457 457"/>
    <region xml:id="r66" anchors="1016 1017"/>
    <region xml:id="r68" anchors="1018 1097"/>
    <region xml:id="r70" anchors="1018 1018"/>
    <region xml:id="r72" anchors="1096 1097"/>
    <region xml:id="r74" anchors="1098 1141"/>
    <region xml:id="r76" anchors="1098 1098"/>
    <region xml:id="r78" anchors="1140 1141"/>
    <region xml:id="r80" anchors="1142 1182"/>
    <region xml:id="r82" anchors="1142 1142"/>
    <region xml:id="r84" anchors="1181 1182"/>
    <region xml:id="r86" anchors="1189 1225"/>
    <region xml:id="r88" anchors="1189 1189"/>
    <region xml:id="r92" anchors="1239 1509"/>
    <region xml:id="r94" anchors="1239 1239"/>
    <region xml:id="r90" anchors="1239 1239"/>
    <region xml:id="r96" anchors="1508 1509"/>
    <region xml:id="r98" anchors="1510 1967"/>
    <region xml:id="r100" anchors="1510 1633"/>
    <region xml:id="r102" anchors="1510 1520"/>
    <region xml:id="r104" anchors="1510 1510"/>
    <region xml:id="r106" anchors="1522 1550"/>
    <region xml:id="r108" anchors="1948 1966"/>
    <region xml:id="r110" anchors="1966 1967"/>
    <region xml:id="r112" anchors="1974 2091"/>
    <region xml:id="r114" anchors="1974 1974"/>
    <region xml:id="r116" anchors="2039 2069"/>
    <region xml:id="r118" anchors="2070 2090"/>
    <region xml:id="r120" anchors="2070 2078"/>
    <region xml:id="r122" anchors="2090 2091"/>
    <region xml:id="r124" anchors="2092 2284"/>
    <region xml:id="r126" anchors="2092 2094"/>
    <region xml:id="r128" anchors="2092 2092"/>
    <region xml:id="r130" anchors="2098 2104"/>
    <region xml:id="r133" anchors="2109 2146"/>
    <region xml:id="r135" anchors="2159 2210"/>
    <region xml:id="r137" anchors="2159 2207"/>
    <region xml:id="r139" anchors="2211 2283"/>
    <region xml:id="r141" anchors="2283 2284"/>
    <region xml:id="r143" anchors="2285 2424"/>
    <region xml:id="r145" anchors="2285 2423"/>
    <region xml:id="r147" anchors="2285 2285"/>
    <region xml:id="r149" anchors="2368 2400"/>
    <region xml:id="r151" anchors="2402 2423"/>
    <region xml:id="r153" anchors="2423 2424"/>
    <region xml:id="r155" anchors="2431 2613"/>
    <region xml:id="r157" anchors="2431 2516"/>
    <region xml:id="r159" anchors="2431 2437"/>
    <region xml:id="r161" anchors="2431 2431"/>
    <region xml:id="r163" anchors="2439 2516"/>
    <region xml:id="r165" anchors="2522 2526"/>
    <region xml:id="r168" anchors="2527 2612"/>
    <region xml:id="r170" anchors="2532 2539"/>
    <region xml:id="r172" anchors="2540 2568"/>
    <region xml:id="r174" anchors="2543 2568"/>
    <region xml:id="r176" anchors="2612 2613"/>
    <region xml:id="r178" anchors="2614 2694"/>
    <region xml:id="r180" anchors="2614 2614"/>
    <region xml:id="r182" anchors="2693 2694"/>
    <region xml:id="r184" anchors="2695 2775"/>
    <region xml:id="r186" anchors="2695 2697"/>
    <region xml:id="r188" anchors="2695 2695"/>
    <region xml:id="r190" anchors="2698 2707"/>
    <region xml:id="r192" anchors="2698 2703"/>
    <region xml:id="r194" anchors="2704 2707"/>
    <region xml:id="r196" anchors="2742 2754"/>
    <region xml:id="r199" anchors="2758 2774"/>
    <region xml:id="r201" anchors="2774 2775"/>
    <region xml:id="r203" anchors="2782 2870"/>
    <region xml:id="r205" anchors="2782 2791"/>
    <region xml:id="r208" anchors="2782 2782"/>
    <region xml:id="r210" anchors="2799 2815"/>
    <region xml:id="r214" anchors="2870 2870"/>
    <region xml:id="r212" anchors="2870 2870"/>
    <node xml:id="n0">
        <link targets="r1"/>
    </node>
    <a label="agent" ref="n0" as="mpqa">
        <fs>
            <f name="id" value="implicit"/>
        </fs>
    </a>
    <a label="agent" ref="n0" as="mpqa">
        <fs>
            <f name="id" value="w"/>
        </fs>
    </a>
    <a label="direct-subjective" ref="n0" as="mpqa"/>
    <a label="expressive-subjectivity" ref="n0" as="mpqa"/>
    <node xml:id="n1">
        <link targets="r6"/>
    </node>
    <a label="split" ref="n1" as="mpqa"/>
    <node xml:id="n10">
        <link targets="r25"/>
    </node>
    <a label="split" ref="n10" as="mpqa"/>
    <node xml:id="n100">
        <link targets="r210"/>
    </node>
    <a label="target" ref="n100" as="mpqa">
        <fs>
            <f name="id" value="w"/>
        </fs>
    </a>
    <node xml:id="n101">
        <link targets="r212"/>
    </node>
    <a label="split" ref="n101" as="mpqa"/>
    <node xml:id="n102">
        <link targets="r214"/>
    </node>
    <a label="split" ref="n102" as="mpqa"/>
    <node xml:id="n11">
        <link targets="r27"/>
    </node>
    <a label="inside" ref="n11" as="mpqa">
        <fs>
            <f name="nested-source" value="w"/>
        </fs>
    </a>
    <node xml:id="n12">
        <link targets="r29"/>
    </node>
    <a label="split" ref="n12" as="mpqa"/>
    <node xml:id="n13">
        <link targets="r31"/>
    </node>
    <a label="inside" ref="n13" as="mpqa">
        <fs>
            <f name="nested-source" value="w"/>
        </fs>
    </a>
    <node xml:id="n14">
        <link targets="r33"/>
    </node>
    <a label="objective-speech-event" ref="n14" as="mpqa">
        <fs>
            <f name="implicit" value="true"/>
            <f name="nested-source" value="w"/>
        </fs>
    </a>
    <node xml:id="n15">
        <link targets="r35"/>
    </node>
    <a label="split" ref="n15" as="mpqa"/>
    <node xml:id="n16">
        <link targets="r37"/>
    </node>
    <a label="inside" ref="n16" as="mpqa">
        <fs>
            <f name="nested-source" value="w"/>
        </fs>
    </a>
    <node xml:id="n17">
        <link targets="r39"/>
    </node>
    <a label="expressive-subjectivity" ref="n17" as="mpqa">
        <fs>
            <f name="intensity" value="high"/>
            <f name="nested-source" value="w"/>
        </fs>
    </a>
    <node xml:id="n18">
        <link targets="r41"/>
    </node>
    <a label="target" ref="n18" as="mpqa">
        <fs>
            <f name="id" value="thishere"/>
        </fs>
    </a>
    <node xml:id="n19">
        <link targets="r43"/>
    </node>
    <a label="direct-subjective" ref="n19" as="mpqa">
        <fs>
            <f name="nested-source" value="w"/>
            <f name="attitude-link" value="exactlythat"/>
            <f name="implicit" value="true"/>
            <f name="expression-intensity" value="neutral"/>
            <f name="intensity" value="medium"/>
        </fs>
    </a>
    <node xml:id="n2">
        <link targets="r8"/>
    </node>
    <a label="split" ref="n2" as="mpqa"/>
    <node xml:id="n20">
        <link targets="r45"/>
    </node>
    <a label="attitude" ref="n20" as="mpqa">
        <fs>
            <f name="id" value="exactlythat"/>
            <f name="target-link" value="thishere"/>
            <f name="intensity" value="medium-high"/>
            <f name="attitude-type" value="arguing-pos"/>
        </fs>
    </a>
    <node xml:id="n21">
        <link targets="r47"/>
    </node>
    <a label="agent" ref="n21" as="mpqa">
        <fs>
            <f name="id" value="cci"/>
        </fs>
    </a>
    <node xml:id="n22">
        <link targets="r49"/>
    </node>
    <a label="split" ref="n22" as="mpqa"/>
    <node xml:id="n23">
        <link targets="r51"/>
    </node>
    <a label="attitude" ref="n23" as="mpqa">
        <fs>
            <f name="id" value="callforsupport"/>
            <f name="target-link" value="yfs"/>
            <f name="intensity" value="medium-high"/>
            <f name="attitude-type" value="sentiment-pos"/>
        </fs>
    </a>
    <a label="inside" ref="n23" as="mpqa">
        <fs>
            <f name="nested-source" value="w"/>
        </fs>
    </a>
    <node xml:id="n24">
        <link targets="r54"/>
    </node>
    <a label="objective-speech-event" ref="n24" as="mpqa">
        <fs>
            <f name="implicit" value="true"/>
            <f name="nested-source" value="w"/>
        </fs>
    </a>
    <node xml:id="n25">
        <link targets="r56"/>
    </node>
    <a label="expressive-subjectivity" ref="n25" as="mpqa">
        <fs>
            <f name="nested-source" value="w"/>
            <f name="polarity" value="positive"/>
            <f name="intensity" value="high"/>
        </fs>
    </a>
    <node xml:id="n26">
        <link targets="r58"/>
    </node>
    <a label="target" ref="n26" as="mpqa">
        <fs>
            <f name="id" value="yfs"/>
        </fs>
    </a>
    <node xml:id="n27">
        <link targets="r60"/>
    </node>
    <a label="split" ref="n27" as="mpqa"/>
    <node xml:id="n28">
        <link targets="r62"/>
    </node>
    <a label="inside" ref="n28" as="mpqa">
        <fs>
            <f name="nested-source" value="w"/>
        </fs>
    </a>
    <node xml:id="n29">
        <link targets="r64"/>
    </node>
    <a label="objective-speech-event" ref="n29" as="mpqa">
        <fs>
            <f name="implicit" value="true"/>
            <f name="nested-source" value="w"/>
        </fs>
    </a>
    <node xml:id="n3">
        <link targets="r10"/>
    </node>
    <a label="inside" ref="n3" as="mpqa">
        <fs>
            <f name="nested-source" value="w"/>
        </fs>
    </a>
    <node xml:id="n30">
        <link targets="r66"/>
    </node>
    <a label="split" ref="n30" as="mpqa"/>
    <node xml:id="n31">
        <link targets="r68"/>
    </node>
    <a label="inside" ref="n31" as="mpqa">
        <fs>
            <f name="nested-source" value="w"/>
        </fs>
    </a>
    <node xml:id="n32">
        <link targets="r70"/>
    </node>
    <a label="objective-speech-event" ref="n32" as="mpqa">
        <fs>
            <f name="implicit" value="true"/>
            <f name="nested-source" value="w"/>
        </fs>
    </a>
    <node xml:id="n33">
        <link targets="r72"/>
    </node>
    <a label="split" ref="n33" as="mpqa"/>
    <node xml:id="n34">
        <link targets="r74"/>
    </node>
    <a label="inside" ref="n34" as="mpqa">
        <fs>
            <f name="nested-source" value="w"/>
        </fs>
    </a>
    <node xml:id="n35">
        <link targets="r76"/>
    </node>
    <a label="objective-speech-event" ref="n35" as="mpqa">
        <fs>
            <f name="implicit" value="true"/>
            <f name="nested-source" value="w"/>
        </fs>
    </a>
    <node xml:id="n36">
        <link targets="r78"/>
    </node>
    <a label="split" ref="n36" as="mpqa"/>
    <node xml:id="n37">
        <link targets="r80"/>
    </node>
    <a label="inside" ref="n37" as="mpqa">
        <fs>
            <f name="nested-source" value="w"/>
        </fs>
    </a>
    <node xml:id="n38">
        <link targets="r82"/>
    </node>
    <a label="objective-speech-event" ref="n38" as="mpqa">
        <fs>
            <f name="implicit" value="true"/>
            <f name="nested-source" value="w"/>
        </fs>
    </a>
    <node xml:id="n39">
        <link targets="r84"/>
    </node>
    <a label="split" ref="n39" as="mpqa"/>
    <node xml:id="n4">
        <link targets="r12"/>
    </node>
    <a label="objective-speech-event" ref="n4" as="mpqa">
        <fs>
            <f name="implicit" value="true"/>
            <f name="nested-source" value="w"/>
        </fs>
    </a>
    <node xml:id="n40">
        <link targets="r86"/>
    </node>
    <a label="inside" ref="n40" as="mpqa">
        <fs>
            <f name="nested-source" value="w"/>
        </fs>
    </a>
    <node xml:id="n41">
        <link targets="r88"/>
    </node>
    <a label="objective-speech-event" ref="n41" as="mpqa">
        <fs>
            <f name="implicit" value="true"/>
            <f name="nested-source" value="w"/>
        </fs>
    </a>
    <node xml:id="n42">
        <link targets="r90"/>
    </node>
    <a label="split" ref="n42" as="mpqa"/>
    <node xml:id="n43">
        <link targets="r92"/>
    </node>
    <a label="inside" ref="n43" as="mpqa">
        <fs>
            <f name="nested-source" value="w"/>
        </fs>
    </a>
    <node xml:id="n44">
        <link targets="r94"/>
    </node>
    <a label="objective-speech-event" ref="n44" as="mpqa">
        <fs>
            <f name="implicit" value="true"/>
            <f name="nested-source" value="w"/>
        </fs>
    </a>
    <node xml:id="n45">
        <link targets="r96"/>
    </node>
    <a label="split" ref="n45" as="mpqa"/>
    <node xml:id="n46">
        <link targets="r98"/>
    </node>
    <a label="inside" ref="n46" as="mpqa">
        <fs>
            <f name="nested-source" value="w"/>
        </fs>
    </a>
    <node xml:id="n47">
        <link targets="r100"/>
    </node>
    <a label="attitude" ref="n47" as="mpqa">
        <fs>
            <f name="id" value="whatsmore"/>
            <f name="target-link" value="mots"/>
            <f name="intensity" value="medium"/>
            <f name="attitude-type" value="arguing-pos"/>
        </fs>
    </a>
    <node xml:id="n48">
        <link targets="r102"/>
    </node>
    <a label="expressive-subjectivity" ref="n48" as="mpqa">
        <fs>
            <f name="nested-source" value="w"/>
            <f name="polarity" value="positive"/>
            <f name="intensity" value="medium"/>
        </fs>
    </a>
    <node xml:id="n49">
        <link targets="r104"/>
    </node>
    <a label="objective-speech-event" ref="n49" as="mpqa">
        <fs>
            <f name="implicit" value="true"/>
            <f name="nested-source" value="w"/>
        </fs>
    </a>
    <node xml:id="n5">
        <link targets="r14"/>
    </node>
    <a label="split" ref="n5" as="mpqa"/>
    <node xml:id="n50">
        <link targets="r106"/>
    </node>
    <a label="target" ref="n50" as="mpqa">
        <fs>
            <f name="id" value="mots"/>
        </fs>
    </a>
    <node xml:id="n51">
        <link targets="r108"/>
    </node>
    <a label="expressive-subjectivity" ref="n51" as="mpqa">
        <fs>
            <f name="intensity" value="low"/>
            <f name="nested-source-uncertain" value=""/>
            <f name="es-uncertain" value="very-uncertain"/>
            <f name="nested-source" value="w"/>
        </fs>
    </a>
    <node xml:id="n52">
        <link targets="r110"/>
    </node>
    <a label="split" ref="n52" as="mpqa"/>
    <node xml:id="n53">
        <link targets="r112"/>
    </node>
    <a label="inside" ref="n53" as="mpqa">
        <fs>
            <f name="nested-source" value="w"/>
        </fs>
    </a>
    <node xml:id="n54">
        <link targets="r114"/>
    </node>
    <a label="direct-subjective" ref="n54" as="mpqa">
        <fs>
            <f name="nested-source" value="w"/>
            <f name="attitude-link" value="couldbe"/>
            <f name="implicit" value="true"/>
            <f name="intensity" value="low"/>
            <f name="expression-intensity" value="neutral"/>
        </fs>
    </a>
    <node xml:id="n55">
        <link targets="r116"/>
    </node>
    <a label="target" ref="n55" as="mpqa">
        <fs>
            <f name="id" value="final"/>
        </fs>
    </a>
    <node xml:id="n56">
        <link targets="r118"/>
    </node>
    <a label="attitude" ref="n56" as="mpqa">
        <fs>
            <f name="id" value="couldbe"/>
            <f name="target-link" value="final"/>
            <f name="intensity" value="low"/>
            <f name="attitude-type" value="speculation"/>
        </fs>
    </a>
    <node xml:id="n57">
        <link targets="r120"/>
    </node>
    <a label="expressive-subjectivity" ref="n57" as="mpqa">
        <fs>
            <f name="intensity" value="low"/>
            <f name="nested-source" value="w"/>
        </fs>
    </a>
    <node xml:id="n58">
        <link targets="r122"/>
    </node>
    <a label="split" ref="n58" as="mpqa"/>
    <node xml:id="n59">
        <link targets="r124"/>
    </node>
    <a label="inside" ref="n59" as="mpqa">
        <fs>
            <f name="nested-source" value="w"/>
        </fs>
    </a>
    <node xml:id="n6">
        <link targets="r16"/>
    </node>
    <a label="inside" ref="n6" as="mpqa">
        <fs>
            <f name="nested-source" value="w"/>
        </fs>
    </a>
    <node xml:id="n60">
        <link targets="r126"/>
    </node>
    <a label="agent" ref="n60" as="mpqa">
        <fs>
            <f name="nested-source" value="w,cci"/>
        </fs>
    </a>
    <node xml:id="n61">
        <link targets="r128"/>
    </node>
    <a label="objective-speech-event" ref="n61" as="mpqa">
        <fs>
            <f name="implicit" value="true"/>
            <f name="nested-source" value="w"/>
        </fs>
    </a>
    <node xml:id="n62">
        <link targets="r130"/>
    </node>
    <a label="attitude" ref="n62" as="mpqa">
        <fs>
            <f name="id" value="asking"/>
            <f name="target-link" value="contrib"/>
            <f name="intensity" value="low-medium"/>
            <f name="attitude-type" value="sentiment-pos"/>
        </fs>
    </a>
    <a label="direct-subjective" ref="n62" as="mpqa">
        <fs>
            <f name="nested-source" value="w,cci"/>
            <f name="polarity" value="positive"/>
            <f name="attitude-link" value="asking,bestbet"/>
            <f name="expression-intensity" value="low"/>
            <f name="intensity" value="low"/>
        </fs>
    </a>
    <node xml:id="n63">
        <link targets="r133"/>
    </node>
    <a label="target" ref="n63" as="mpqa">
        <fs>
            <f name="id" value="contrib"/>
        </fs>
    </a>
    <node xml:id="n64">
        <link targets="r135"/>
    </node>
    <a label="attitude" ref="n64" as="mpqa">
        <fs>
            <f name="id" value="bestbet"/>
            <f name="target-link" value="manymany"/>
            <f name="intensity" value="medium-high"/>
            <f name="attitude-type" value="arguing-pos"/>
        </fs>
    </a>
    <node xml:id="n65">
        <link targets="r137"/>
    </node>
    <a label="expressive-subjectivity" ref="n65" as="mpqa">
        <fs>
            <f name="nested-source" value="w,cci"/>
            <f name="polarity" value="positive"/>
            <f name="intensity" value="low"/>
        </fs>
    </a>
    <node xml:id="n66">
        <link targets="r139"/>
    </node>
    <a label="target" ref="n66" as="mpqa">
        <fs>
            <f name="id" value="manymany"/>
        </fs>
    </a>
    <node xml:id="n67">
        <link targets="r141"/>
    </node>
    <a label="split" ref="n67" as="mpqa"/>
    <node xml:id="n68">
        <link targets="r143"/>
    </node>
    <a label="inside" ref="n68" as="mpqa">
        <fs>
            <f name="nested-source" value="w"/>
        </fs>
    </a>
    <node xml:id="n69">
        <link targets="r145"/>
    </node>
    <a label="attitude" ref="n69" as="mpqa">
        <fs>
            <f name="id" value="counts"/>
            <f name="target-link" value="nl"/>
            <f name="intensity" value="low-medium"/>
            <f name="attitude-type" value="arguing-pos"/>
        </fs>
    </a>
    <node xml:id="n7">
        <link targets="r18"/>
    </node>
    <a label="attitude" ref="n7" as="mpqa">
        <fs>
            <f name="id" value="cher"/>
            <f name="target-link" value="lecteur"/>
            <f name="intensity" value="medium"/>
            <f name="attitude-type" value="sentiment-pos"/>
        </fs>
    </a>
    <a label="expressive-subjectivity" ref="n7" as="mpqa">
        <fs>
            <f name="nested-source" value="w"/>
            <f name="polarity" value="positive"/>
            <f name="intensity" value="medium"/>
        </fs>
    </a>
    <node xml:id="n70">
        <link targets="r147"/>
    </node>
    <a label="direct-subjective" ref="n70" as="mpqa">
        <fs>
            <f name="nested-source" value="w"/>
            <f name="attitude-link" value="counts"/>
            <f name="annotation-uncertain" value=""/>
            <f name="implicit" value="true"/>
            <f name="expression-intensity" value="neutral"/>
            <f name="intensity" value="medium"/>
        </fs>
    </a>
    <node xml:id="n71">
        <link targets="r149"/>
    </node>
    <a label="target" ref="n71" as="mpqa">
        <fs>
            <f name="id" value="nl"/>
        </fs>
    </a>
    <node xml:id="n72">
        <link targets="r151"/>
    </node>
    <a label="expressive-subjectivity" ref="n72" as="mpqa">
        <fs>
            <f name="intensity" value="medium"/>
            <f name="nested-source" value="w"/>
        </fs>
    </a>
    <node xml:id="n73">
        <link targets="r153"/>
    </node>
    <a label="split" ref="n73" as="mpqa"/>
    <node xml:id="n74">
        <link targets="r155"/>
    </node>
    <a label="inside" ref="n74" as="mpqa">
        <fs>
            <f name="nested-source" value="w"/>
        </fs>
    </a>
    <node xml:id="n75">
        <link targets="r157"/>
    </node>
    <a label="attitude" ref="n75" as="mpqa">
        <fs>
            <f name="id" value="askforgiving"/>
            <f name="target-link" value="makegift"/>
            <f name="intensity" value="low-medium"/>
            <f name="attitude-type" value="sentiment-pos"/>
        </fs>
    </a>
    <node xml:id="n76">
        <link targets="r159"/>
    </node>
    <a label="expressive-subjectivity" ref="n76" as="mpqa">
        <fs>
            <f name="nested-source" value="w"/>
            <f name="polarity" value="positive"/>
            <f name="intensity" value="medium"/>
        </fs>
    </a>
    <node xml:id="n77">
        <link targets="r161"/>
    </node>
    <a label="direct-subjective" ref="n77" as="mpqa">
        <fs>
            <f name="nested-source" value="w"/>
            <f name="attitude-link" value="askforgiving"/>
            <f name="implicit" value="true"/>
            <f name="expression-intensity" value="neutral"/>
            <f name="intensity" value="medium"/>
        </fs>
    </a>
    <node xml:id="n78">
        <link targets="r163"/>
    </node>
    <a label="target" ref="n78" as="mpqa">
        <fs>
            <f name="id" value="makegift"/>
        </fs>
    </a>
    <node xml:id="n79">
        <link targets="r165"/>
    </node>
    <a label="direct-subjective" ref="n79" as="mpqa">
        <fs>
            <f name="nested-source" value="w,you"/>
            <f name="insubstantial" value="c2"/>
            <f name="attitude-link" value="doknow"/>
            <f name="intensity" value="low"/>
            <f name="expression-intensity" value="neutral"/>
        </fs>
    </a>
    <a label="attitude" ref="n79" as="mpqa">
        <fs>
            <f name="id" value="doknow"/>
            <f name="target-link" value="compdoes"/>
            <f name="intensity" value="low-medium"/>
            <f name="attitude-type" value="other-attitude"/>
        </fs>
    </a>
    <node xml:id="n8">
        <link targets="r21"/>
    </node>
    <a label="direct-subjective" ref="n8" as="mpqa">
        <fs>
            <f name="expression-intensity" value="neutral"/>
            <f name="intensity" value="medium"/>
            <f name="attitude-link" value="cher"/>
            <f name="nested-source" value="w"/>
        </fs>
    </a>
    <node xml:id="n80">
        <link targets="r168"/>
    </node>
    <a label="target" ref="n80" as="mpqa">
        <fs>
            <f name="id" value="compdoes"/>
        </fs>
    </a>
    <node xml:id="n81">
        <link targets="r170"/>
    </node>
    <a label="target" ref="n81" as="mpqa">
        <fs>
            <f name="id" value="yourcompany"/>
        </fs>
    </a>
    <node xml:id="n82">
        <link targets="r172"/>
    </node>
    <a label="attitude" ref="n82" as="mpqa">
        <fs>
            <f name="id" value="dopart"/>
            <f name="target-link" value="yourcompany"/>
            <f name="intensity" value="medium"/>
            <f name="attitude-type" value="sentiment-pos"/>
        </fs>
    </a>
    <node xml:id="n83">
        <link targets="r174"/>
    </node>
    <a label="expressive-subjectivity" ref="n83" as="mpqa">
        <fs>
            <f name="nested-source" value="w,you"/>
            <f name="polarity" value="positive"/>
            <f name="intensity" value="high"/>
        </fs>
    </a>
    <node xml:id="n84">
        <link targets="r176"/>
    </node>
    <a label="split" ref="n84" as="mpqa"/>
    <node xml:id="n85">
        <link targets="r178"/>
    </node>
    <a label="inside" ref="n85" as="mpqa">
        <fs>
            <f name="nested-source" value="w"/>
        </fs>
    </a>
    <node xml:id="n86">
        <link targets="r180"/>
    </node>
    <a label="objective-speech-event" ref="n86" as="mpqa">
        <fs>
            <f name="implicit" value="true"/>
            <f name="nested-source" value="w"/>
        </fs>
    </a>
    <node xml:id="n87">
        <link targets="r182"/>
    </node>
    <a label="split" ref="n87" as="mpqa"/>
    <node xml:id="n88">
        <link targets="r184"/>
    </node>
    <a label="inside" ref="n88" as="mpqa">
        <fs>
            <f name="nested-source" value="w"/>
        </fs>
    </a>
    <node xml:id="n89">
        <link targets="r186"/>
    </node>
    <a label="agent" ref="n89" as="mpqa">
        <fs>
            <f name="nested-source" value="w,cci"/>
        </fs>
    </a>
    <node xml:id="n9">
        <link targets="r23"/>
    </node>
    <a label="target" ref="n9" as="mpqa">
        <fs>
            <f name="id" value="lecteur"/>
        </fs>
    </a>
    <node xml:id="n90">
        <link targets="r188"/>
    </node>
    <a label="objective-speech-event" ref="n90" as="mpqa">
        <fs>
            <f name="implicit" value="true"/>
            <f name="nested-source" value="w"/>
        </fs>
    </a>
    <node xml:id="n91">
        <link targets="r190"/>
    </node>
    <a label="attitude" ref="n91" as="mpqa">
        <fs>
            <f name="id" value="danke"/>
            <f name="target-link" value="toi"/>
            <f name="intensity" value="low-medium"/>
            <f name="attitude-type" value="sentiment-pos"/>
        </fs>
    </a>
    <node xml:id="n92">
        <link targets="r192"/>
    </node>
    <a label="direct-subjective" ref="n92" as="mpqa">
        <fs>
            <f name="nested-source" value="w,cci"/>
            <f name="polarity" value="positive"/>
            <f name="attitude-link" value="danke"/>
            <f name="expression-intensity" value="medium"/>
            <f name="intensity" value="medium"/>
        </fs>
    </a>
    <node xml:id="n93">
        <link targets="r194"/>
    </node>
    <a label="target" ref="n93" as="mpqa">
        <fs>
            <f name="id" value="toi"/>
            <f name="target-uncertain" value=""/>
        </fs>
    </a>
    <node xml:id="n94">
        <link targets="r196"/>
    </node>
    <a label="direct-subjective" ref="n94" as="mpqa">
        <fs>
            <f name="nested-source" value="w,cci"/>
            <f name="polarity" value="positive"/>
            <f name="attitude-link" value="vorfreude"/>
            <f name="expression-intensity" value="medium"/>
            <f name="intensity" value="medium"/>
        </fs>
    </a>
    <a label="attitude" ref="n94" as="mpqa">
        <fs>
            <f name="attitude-type" value="sentiment-pos"/>
            <f name="contrast" value=""/>
            <f name="id" value="vorfreude"/>
            <f name="target-link" value="hearhear"/>
            <f name="intensity" value="low-medium"/>
        </fs>
    </a>
    <node xml:id="n95">
        <link targets="r199"/>
    </node>
    <a label="target" ref="n95" as="mpqa">
        <fs>
            <f name="id" value="hearhear"/>
        </fs>
    </a>
    <node xml:id="n96">
        <link targets="r201"/>
    </node>
    <a label="split" ref="n96" as="mpqa"/>
    <node xml:id="n97">
        <link targets="r203"/>
    </node>
    <a label="inside" ref="n97" as="mpqa">
        <fs>
            <f name="nested-source" value="w"/>
        </fs>
    </a>
    <node xml:id="n98">
        <link targets="r205"/>
    </node>
    <a label="expressive-subjectivity" ref="n98" as="mpqa">
        <fs>
            <f name="nested-source" value="w"/>
            <f name="polarity" value="positive"/>
            <f name="intensity" value="low"/>
        </fs>
    </a>
    <a label="attitude" ref="n98" as="mpqa">
        <fs>
            <f name="id" value="since"/>
            <f name="target-link" value=""/>
            <f name="intensity" value="low"/>
            <f name="attitude-type" value="sentiment-pos"/>
        </fs>
    </a>
    <node xml:id="n99">
        <link targets="r208"/>
    </node>
    <a label="direct-subjective" ref="n99" as="mpqa">
        <fs>
            <f name="nested-source" value="w"/>
            <f name="polarity" value=""/>
            <f name="attitude-link" value="since"/>
            <f name="implicit" value="true"/>
            <f name="expression-intensity" value="neutral"/>
            <f name="intensity" value="low"/>
        </fs>
    </a>
</graph>
